cmip_ref_metrics_esmvaltool/__init__.py
cmip_ref_metrics_esmvaltool/_version.py
cmip_ref_metrics_esmvaltool/py.typed
cmip_ref_metrics_esmvaltool/recipe.py
cmip_ref_metrics_esmvaltool/recipes.txt
cmip_ref_metrics_esmvaltool/types.py
cmip_ref_metrics_esmvaltool/dataset_registry/data.txt
cmip_ref_metrics_esmvaltool/metrics/__init__.py
cmip_ref_metrics_esmvaltool/metrics/base.py
cmip_ref_metrics_esmvaltool/metrics/climate_at_global_warming_levels.py
cmip_ref_metrics_esmvaltool/metrics/ecs.py
cmip_ref_metrics_esmvaltool/metrics/example.py
cmip_ref_metrics_esmvaltool/metrics/sea_ice_area_seasonal_cycle.py
cmip_ref_metrics_esmvaltool/metrics/tcr.py
cmip_ref_metrics_esmvaltool/metrics/tcre.py
cmip_ref_metrics_esmvaltool/metrics/zec.py
cmip_ref_metrics_esmvaltool/requirements/conda-lock.yml
cmip_ref_metrics_esmvaltool/requirements/environment.yml
cmip_ref_metrics_esmvaltool-0.4.1.dist-info/METADATA
cmip_ref_metrics_esmvaltool-0.4.1.dist-info/WHEEL
cmip_ref_metrics_esmvaltool-0.4.1.dist-info/licenses/LICENCE
cmip_ref_metrics_esmvaltool-0.4.1.dist-info/licenses/NOTICE
cmip_ref_metrics_esmvaltool-0.4.1.dist-info/RECORD
