Metadata-Version: 2.4
Name: cmip_ref_metrics_esmvaltool
Version: 0.4.1
Summary: ESMValTool metrics provider for the CMIP Rapid Evaluation Framework
Author-email: ESMValTool development team <esmvaltool-dev@listserv.dfn.de>
License: Apache-2.0
License-File: LICENCE
License-File: NOTICE
Classifier: Development Status :: 4 - Beta
Classifier: Intended Audience :: Developers
Classifier: Intended Audience :: Science/Research
Classifier: Operating System :: OS Independent
Classifier: Programming Language :: Python
Classifier: Programming Language :: Python :: 3
Classifier: Programming Language :: Python :: 3.11
Classifier: Programming Language :: Python :: 3.12
Classifier: Programming Language :: Python :: 3.13
Classifier: Topic :: Scientific/Engineering
Requires-Python: >=3.11
Requires-Dist: cmip-ref-core
Requires-Dist: pooch>=1.8
Requires-Dist: ruamel-yaml>=0.18
Requires-Dist: xarray>=2023.3.0
